matbench_discovery/__init__.py
matbench_discovery/data.py
matbench_discovery/energy.py
matbench_discovery/enums.py
matbench_discovery/metrics.py
matbench_discovery/models.py
matbench_discovery/plots.py
matbench_discovery/preds.py
matbench_discovery/slurm.py
matbench_discovery/structure.py
matbench_discovery/figshare/1.0.0.json
matbench_discovery/figshare/readme.md
matbench_discovery-1.3.1.dist-info/METADATA
matbench_discovery-1.3.1.dist-info/WHEEL
matbench_discovery-1.3.1.dist-info/top_level.txt
matbench_discovery-1.3.1.dist-info/RECORD
