Metadata-Version: 2.1
Name: matbench-discovery
Version: 1.3.1
Summary: A benchmark for machine learning energy models on inorganic crystal stability prediction from unrelaxed structures
Author-email: Janosh Riebesell <janosh.riebesell@gmail.com>
License: MIT License
Project-URL: Homepage, https://janosh.github.io/matbench-discovery
Project-URL: Repo, https://github.com/janosh/matbench-discovery
Project-URL: Package, https://pypi.org/project/matbench-discovery
Keywords: Bayesian optimization,convex hull,high-throughput search,inorganic crystal stability,interatomic potential,machine learning,materials discovery
Classifier: Intended Audience :: Science/Research
Classifier: License :: OSI Approved :: MIT License
Classifier: Operating System :: OS Independent
Classifier: Programming Language :: Python :: 3.11
Classifier: Topic :: Scientific/Engineering :: Artificial Intelligence
Classifier: Topic :: Scientific/Engineering :: Chemistry
Classifier: Topic :: Scientific/Engineering :: Physics
Requires-Python: >=3.11
Requires-Dist: ase >=3.23
Requires-Dist: matplotlib >=3.9.2
Requires-Dist: numpy >=1.26
Requires-Dist: pandas >=2.2.2
Requires-Dist: plotly >=5.23
Requires-Dist: pymatgen >=2024.8.9
Requires-Dist: pymatviz[df-pdf-export,df-svg-export,export-figs] >=0.11
Requires-Dist: scikit-learn >=1.5
Requires-Dist: scipy >=1.13
Requires-Dist: seaborn >=0.13
Requires-Dist: tqdm >=4.66
Requires-Dist: wandb >=0.17
Provides-Extra: 3d-structures
Requires-Dist: crystal-toolkit >=2023.11.3 ; extra == '3d-structures'
Provides-Extra: fetch-wbm-data
Requires-Dist: gdown >=5.1 ; extra == 'fetch-wbm-data'
Provides-Extra: make-wbm-umap
Requires-Dist: umap-learn >=0.5.5 ; extra == 'make-wbm-umap'
Provides-Extra: running-models
Requires-Dist: alignn >=2024.1.14 ; extra == 'running-models'
Requires-Dist: chgnet >=0.3.0 ; extra == 'running-models'
Requires-Dist: jarvis-tools ; extra == 'running-models'
Requires-Dist: m3gnet >=0.2.4 ; extra == 'running-models'
Requires-Dist: mace-torch >=0.3.6 ; extra == 'running-models'
Requires-Dist: maml >=2023.9.9 ; extra == 'running-models'
Requires-Dist: megnet >=1.3.2 ; extra == 'running-models'
Provides-Extra: test
Requires-Dist: pytest-cov >=5 ; extra == 'test'
Requires-Dist: pytest >=8.1 ; extra == 'test'
